neres/__init__.py
neres/cli.py
neres/newrelic.py
neres/session.py
neres/spinner.py
neres/urls.py
neres-0.5.1.dist-info/LICENSE
neres-0.5.1.dist-info/METADATA
neres-0.5.1.dist-info/WHEEL
neres-0.5.1.dist-info/entry_points.txt
neres-0.5.1.dist-info/top_level.txt
neres-0.5.1.dist-info/RECORD
