Metadata-Version: 2.1
Name: neres
Version: 0.5.1
Summary: (unofficial) NewRelic Synthetics CLI
Home-page: https://github.com/glogiotatidis/neres
Author: Giorgos Logiotatidis
Author-email: giorgos@sealabs.net
License: GNU General Public License v3
Keywords: neres
Platform: UNKNOWN
Classifier: Development Status :: 5 - Production/Stable
Classifier: Intended Audience :: Developers
Classifier: License :: OSI Approved :: GNU General Public License v3 (GPLv3)
Classifier: Natural Language :: English
Classifier: Programming Language :: Python :: 2
Classifier: Programming Language :: Python :: 2.6
Classifier: Programming Language :: Python :: 2.7
Classifier: Programming Language :: Python :: 3
Classifier: Programming Language :: Python :: 3.3
Classifier: Programming Language :: Python :: 3.4
Classifier: Programming Language :: Python :: 3.5
Requires-Dist: python-decouple (==3.0)
Requires-Dist: requests (==2.22.0)
Requires-Dist: click (==7.0)
Requires-Dist: humanize (==0.5.1)
Requires-Dist: terminaltables (==3.1.0)
Requires-Dist: enum34 (==1.1.6)
Requires-Dist: PyYAML (==5.1.1)
Requires-Dist: yamlordereddictloader (==0.3.0)
Requires-Dist: certifi (==2018.10.15)
Requires-Dist: chardet (==3.0.4)
Requires-Dist: urllib3 (==1.25.3)
Requires-Dist: idna (==2.7)
Requires-Dist: entrypoints (==0.3)
